{
  "meta": {
    "source_file": "Sefer Etz Chaim - he - Sefer Etz Chaim.json",
    "section_index": 606,
    "section_hns": "606.1",
    "path_trace": [
      "text#14",
      "#2",
      "39",
      "11",
      "21"
    ],
    "paren_count": 1
  },
  "text_he": "(יט) יש נשמות בני אדם שבאים מזווג או\"א דאצילות והם אחים קטנים לזו\"ן שהם אחים הגדולים מהם שיצאו בראשונה קודם להם ובצאת אלו האחים הגדולים מיסוד אמא בסוד לידה הניחו שרשם למעלה ולכן א\"א שאמא תעלה מ\"ן לגבי אבא אם לא שיעלו שם זו\"ן שהניחו שרשם שם ואז ע\"י האחים הגדולים האלו שהם זו\"ן יכולין הנשמות שהם האחים הקטנים להתחבר עמהם ולהעלות באמא מ\"ן אך לא הם לבדם אלא על ידי שיתחברו שם זו\"ן ויעלו זו\"ן עמה. [הגהה - צמח וז\"א נקרא גדול בסוד בני בכורי ישראל והשאר נשמות הצדיקים שיצאו אחריו כנ\"ל:",
  "parentheses": [
    {
      "hns": "606.1.1",
      "text": "יט"
    }
  ]
}