{
  "meta": {
    "source_file": "Sefer Etz Chaim - he - Sefer Etz Chaim.json",
    "section_index": 404,
    "section_hns": "404.1",
    "path_trace": [
      "text#14",
      "#2",
      "26",
      "2",
      "2"
    ],
    "paren_count": 0
  },
  "text_he": "מ\"ק דע כי יש רמ\"ח אברים בעיבור ורמ\"ח ביניקה ורמ\"ח אברים בגדלות והם סוד ג' מיני רמ\"ח וז\"ס רחם רחמתים לראש גבר שהוא ז\"א שיש בו ג' רמ\"ח רחם א' רחמתים תרי הרי ג' רחמים והרמ\"ח של עיבור הוא כך כי אחוריים דאלהים גימטריא ר' ועם ט\"ו אותיותיהן ועם כולל גימטריא רי\"ו ובכח שם זה נאמר בפרעה וחילו ירה בים ותוסיף ל\"ב נתיבות שהם כולם אלהים יהיה כולם רמ\"ח והרמ\"ח של קטנות הוא ס\"ג וי' אותיות הרי ע\"ג ומ\"ה וכ\"ו ע\"א וב\"ן ברבוע באחורים פשוטים ג\"פ ע\"ב הרי רי\"ו ועם ל\"ב נתיבות שהם ל\"ב אלקים הרי רמ\"ח והרמ\"ח דגדלות הם ע\"ב ס\"ג מ\"ה ב\"ן גימטריא רל\"ב וי\"ו אותיות שבד' שמות הנ\"ל בהיותן פשוטים הרי רמ\"ח:",
  "parentheses": []
}